pydsge/__init__.py
pydsge/__version__.py
pydsge/clsmethods.py
pydsge/engine.py
pydsge/estimation.py
pydsge/filtering.py
pydsge/gensys.py
pydsge/mcmc.py
pydsge/mpile.py
pydsge/parser.py
pydsge/stats.py
pydsge/symbols.py
pydsge/tools.py
pydsge/utils.py
pydsge/examples/dfi.yaml
pydsge/examples/dfi_doc0_meta.npz
pydsge/examples/dfi_doc0_res.npz
pydsge/examples/dfi_doc0_sampler.h5
pydsge/examples/dfi_funcs.py
pydsge/examples/dfi_sampler.h5
pydsge/examples/minimal_nk.yaml
pydsge/examples/tsdata.csv
pydsge/tests/export_getting_started_to_pkl.py
pydsge/tests/test_estimation.py
pydsge/tests/test_model.py
pydsge/tests/test_parser.py
pydsge/tests/test_processing.py
pydsge/tests/resources/estimation.npz
pydsge/tests/resources/getting_started_stable.npz
pydsge-0.2.6.dist-info/licenses/LICENSE
pydsge-0.2.6.dist-info/METADATA
pydsge-0.2.6.dist-info/WHEEL
pydsge-0.2.6.dist-info/top_level.txt
pydsge-0.2.6.dist-info/RECORD
