Metadata-Version: 2.4
Name: pydsge
Version: 0.2.6
Summary: Solve, filter and estimate DSGE models with occasionaly binding constraints
Home-page: https://pydsge.readthedocs.io/en/latest/index.html
Author: Gregor Boehl
Author-email: admin@gregorboehl.com
License: MIT
Classifier: License :: OSI Approved :: MIT License
Classifier: Programming Language :: Python :: 3
Classifier: Programming Language :: Python :: 3.9
License-File: LICENSE
Requires-Dist: numba
Requires-Dist: emcee
Requires-Dist: numpy
Requires-Dist: pandas
Requires-Dist: pathos
Requires-Dist: dill
Requires-Dist: tqdm
Requires-Dist: cloudpickle
Requires-Dist: h5py
Requires-Dist: pyyaml
Requires-Dist: scipy
Requires-Dist: sympy>=1.12
Requires-Dist: emcwrap>=0.2.5
Requires-Dist: grgrlib>=0.1.15
Requires-Dist: econsieve>=0.0.9
Requires-Dist: threadpoolctl>=3.1.0
Dynamic: author
Dynamic: author-email
Dynamic: classifier
Dynamic: description
Dynamic: description-content-type
Dynamic: home-page
Dynamic: license
Dynamic: license-file
Dynamic: requires-dist
Dynamic: summary
